
[
  {
    "id": 1,
    "nome": "Bruschetta de Tomate",
    "categoria": "Entradas",
    "ingredientes": [
      "6 fatias de pão italiano",
      "4 tomates maduros picados",
      "1/4 xícara de manjericão fresco",
      "2 dentes de alho picados",
      "3 colheres de azeite extra virgem",
      "Sal e pimenta a gosto",
      "1 colher de vinagre balsâmico"
    ],
    "modoPreparo": "Preaqueça o forno a 200°C. Corte o pão em fatias e disponha em uma assadeira. Leve ao forno por 5 minutos até ficarem dourados. Misture os tomates, alho, manjericão, azeite e vinagre. Tempere com sal e pimenta. Distribua a mistura sobre as fatias de pão. Sirva imediatamente.",
    "tempoPreparo": "20 min",
    "porcoes": "6 porções",
    "imagem": "/images/bruschetta.jpg"
  },
  {
    "id": 2,
    "nome": "Bolinho de Bacalhau",
    "categoria": "Entradas",
    "ingredientes": [
      "500g de bacalhau dessalgado",
      "500g de batatas cozidas",
      "2 ovos",
      "1 cebola picada",
      "Salsinha picada a gosto",
      "Sal e pimenta a gosto",
      "Óleo para fritar"
    ],
    "modoPreparo": "Cozinhe o bacalhau e desfie. Amasse as batatas cozidas. Misture o bacalhau, batatas, ovos, cebola e salsinha. Tempere com sal e pimenta. Modele os bolinhos com as mãos. Frite em óleo quente até dourar.",
    "tempoPreparo": "45 min",
    "porcoes": "20 unidades",
    "imagem": "/images/bolinho-bacalhau.jpg"
  },
  {
    "id": 3,
    "nome": "Carpaccio de Carne",
    "categoria": "Entradas",
    "ingredientes": [
      "300g de filé mignon congelado",
      "Rúcula a gosto",
      "Lascas de parmesão",
      "Alcaparras a gosto",
      "Azeite extra virgem",
      "Suco de 1 limão",
      "Sal e pimenta a gosto"
    ],
    "modoPreparo": "Corte o filé mignon congelado em fatias bem finas. Disponha as fatias em um prato. Cubra com rúcula e lascas de parmesão. Adicione as alcaparras. Regue com azeite e suco de limão. Sirva gelado.",
    "tempoPreparo": "15 min",
    "porcoes": "4 porções",
    "imagem": "/images/carpaccio.jpg"
  },
  {
    "id": 4,
    "nome": "Frango Grelhado com Legumes",
    "categoria": "Pratos Principais",
    "ingredientes": [
      "4 filés de peito de frango",
      "2 abobrinhas fatiadas",
      "1 berinjela fatiada",
      "2 pimentões coloridos",
      "3 colheres de azeite",
      "Alecrim fresco",
      "Sal e pimenta a gosto"
    ],
    "modoPreparo": "Tempere o frango com sal, pimenta e limão. Grelhe o frango em fogo médio por 6 minutos de cada lado. Tempere os legumes com azeite e grelhe-os até ficarem dourados. Monte o prato com o frango e os legumes.",
    "tempoPreparo": "50 min",
    "porcoes": "4 porções",
    "imagem": "/images/frango-grelhado.jpg"
  },
  {
    "id": 5,
    "nome": "Lasanha à Bolonhesa",
    "categoria": "Pratos Principais",
    "ingredientes": [
      "500g de massa para lasanha",
      "500g de carne moída",
      "2 latas de molho de tomate",
      "200g de queijo mussarela",
      "Molho bechamel"
    ],
    "modoPreparo": "Refogue a carne com temperos e molho de tomate. Em um refratário, intercale camadas de massa, molho bolonhesa, molho branco e queijo. Leve ao forno a 200°C por 30 minutos.",
    "tempoPreparo": "1h 30min",
    "porcoes": "8 porções",
    "imagem": "/images/lasanha.jpg"
  },
  {
    "id": 6,
    "nome": "Risoto de Cogumelos",
    "categoria": "Pratos Principais",
    "ingredientes": [
      "2 xícaras de arroz arbóreo",
      "300g de cogumelos variados",
      "1/2 xícara de vinho branco seco",
      "1 litro de caldo de legumes"
    ],
    "modoPreparo": "Refogue os cogumelos e o arroz. Adicione o vinho e mexa até evaporar. Acrescente o caldo aos poucos, mexendo sempre. Finalize com manteiga e parmesão.",
    "tempoPreparo": "40 min",
    "porcoes": "4 porções",
    "imagem": "/images/risoto.jpg"
  },
  {
    "id": 7,
    "nome": "Arroz de Forno com Frango",
    "categoria": "Pratos Secundários",
    "ingredientes": [
      "4 xícaras de arroz cozido",
      "2 xícaras de frango desfiado",
      "200g de mussarela ralada",
      "1 xícara de molho de tomate"
    ],
    "modoPreparo": "Misture o arroz, frango e molho. Coloque em um refratário, cubra com mussarela e leve ao forno a 180°C por 25 minutos até gratinar.",
    "tempoPreparo": "40 min",
    "porcoes": "6 porções",
    "imagem": "/images/arroz-forno.jpg"
  },
  {
    "id": 8,
    "nome": "Salada Caesar",
    "categoria": "Pratos Secundários",
    "ingredientes": [
      "1 pé de alface romana",
      "100g de croutons",
      "Peito de frango grelhado",
      "Molho Caesar"
    ],
    "modoPreparo": "Rasgue a alface, adicione o frango em tiras e os croutons. Regue com o molho Caesar e finalize com parmesão em lascas.",
    "tempoPreparo": "20 min",
    "porcoes": "2 porções",
    "imagem": "/images/salada-caesar.jpg"
  },
  {
    "id": 9,
    "nome": "Purê de Batatas",
    "categoria": "Pratos Secundários",
    "ingredientes": [
      "1kg de batatas",
      "200ml de leite quente",
      "50g de manteiga",
      "Sal e noz-moscada"
    ],
    "modoPreparo": "Cozinhe as batatas e amasse-as. Misture a manteiga e o leite quente aos poucos até ficar cremoso. Tempere com sal e noz-moscada.",
    "tempoPreparo": "30 min",
    "porcoes": "6 porções",
    "imagem": "/images/pure-batatas.jpg"
  },
  {
    "id": 10,
    "nome": "Pudim de Leite Condensado",
    "categoria": "Sobremesas",
    "ingredientes": [
      "1 lata de leite condensado",
      "1 lata de leite",
      "3 ovos",
      "1 xícara de açúcar para calda"
    ],
    "modoPreparo": "Faça a calda de açúcar na forma. Bata os outros ingredientes no liquidificador, despeje na forma e asse em banho-maria por 1 hora.",
    "tempoPreparo": "1h 30min",
    "porcoes": "10 porções",
    "imagem": "/images/pudim.jpg"
  },
  {
    "id": 11,
    "nome": "Brigadeiro Gourmet",
    "categoria": "Sobremesas",
    "ingredientes": [
      "1 lata de leite condensado",
      "4 colheres de chocolate em pó",
      "1 colher de manteiga",
      "Granulado"
    ],
    "modoPreparo": "Cozinhe os ingredientes em fogo médio mexendo sempre. Quando desgrudar do fundo, deixe esfriar, enrole e passe no granulado.",
    "tempoPreparo": "30 min",
    "porcoes": "30 unidades",
    "imagem": "/images/brigadeiro.jpg"
  },
  {
    "id": 12,
    "nome": "Mousse de Maracujá",
    "categoria": "Sobremesas",
    "ingredientes": [
      "1 lata de leite condensado",
      "1 lata de creme de leite",
      "1/2 xícara de suco de maracujá concentrado"
    ],
    "modoPreparo": "Bata tudo no liquidificador. Despeje em taças e leve à geladeira por no mínimo 4 horas antes de servir.",
    "tempoPreparo": "20 min",
    "porcoes": "8 porções",
    "imagem": "/images/mousse-maracuja.jpg"
  },
  {
    "id": 13,
    "nome": "Caipirinha Clássica",
    "categoria": "Bebidas",
    "ingredientes": [
      "1 limão-taiti",
      "2 colheres de açúcar",
      "60ml de cachaça",
      "Gelo"
    ],
    "modoPreparo": "Pique o limão, amasse com açúcar num copo. Adicione a cachaça e o gelo. Misture bem e sirva.",
    "tempoPreparo": "5 min",
    "porcoes": "1 porção",
    "imagem": "/images/caipirinha.jpg"
  },
  {
    "id": 14,
    "nome": "Suco Verde Detox",
    "categoria": "Bebidas",
    "ingredientes": [
      "1 folha de couve",
      "1 maçã verde",
      "Suco de 1 limão",
      "200ml de água de coco"
    ],
    "modoPreparo": "Bata todos os ingredientes no liquidificador. Coe se preferir e sirva bem gelado.",
    "tempoPreparo": "10 min",
    "porcoes": "2 porções",
    "imagem": "/images/suco-verde.jpg"
  },
  {
    "id": 15,
    "nome": "Chocolate Quente Cremoso",
    "categoria": "Bebidas",
    "ingredientes": [
      "500ml de leite",
      "3 colheres de chocolate em pó",
      "2 colheres de amido de milho",
      "Açúcar a gosto"
    ],
    "modoPreparo": "Dissolva o amido no leite frio, junte o chocolate e o açúcar. Leve ao fogo mexendo sempre até engrossar.",
    "tempoPreparo": "15 min",
    "porcoes": "3 porções",
    "imagem": "/images/chocolate-quente.jpg"
  }
]